Metadata-Version: 2.1
Name: probator-auth-saml
Version: 1.2.2
Summary: SAML user authentication
Home-page: https://gitlab.com/probator/probator-auth-saml/
Author: Asbjorn Kjaer
Author-email: bunjiboys+probator@gmail.com
License: License :: OSI Approved :: Apache Software License
Keywords: cloud security
Platform: UNKNOWN
Classifier: Development Status :: 4 - Beta
Classifier: Intended Audience :: System Administrators
Classifier: Intended Audience :: Information Technology
Classifier: License :: OSI Approved :: Apache Software License
Classifier: Programming Language :: Python :: 3.7
Classifier: Framework :: Flask
Classifier: Framework :: Sphinx
Classifier: Operating System :: MacOS :: MacOS X
Classifier: Operating System :: POSIX :: Linux
Classifier: Operating System :: Unix
Classifier: Environment :: Console
Classifier: Natural Language :: English
Classifier: Topic :: Security
Classifier: Topic :: Utilities
Requires-Python: ~=3.7
Provides-Extra: test
Provides-Extra: dev
